whapi/__init__.py
whapi/exceptions.py
whapi-0.6.2.dist-info/LICENSE.md
whapi-0.6.2.dist-info/METADATA
whapi-0.6.2.dist-info/WHEEL
whapi-0.6.2.dist-info/top_level.txt
whapi-0.6.2.dist-info/RECORD
