Metadata-Version: 2.1
Name: whapi
Version: 0.6.2
Summary: An unofficial WikiHow API wrapper
Home-page: https://github.com/killhamster/WHAPI
Author: killhamster
Author-email: killhamster@gmail.com
License: MIT
Platform: UNKNOWN
Classifier: Programming Language :: Python :: 3
Classifier: License :: OSI Approved :: MIT License
Classifier: Operating System :: OS Independent
Requires-Dist: requests
Requires-Dist: bs4
